sage/__init__.py
sage/edge/__init__.py
sage/edge/_version.py
sage/edge/app.py
sage/edge/server.py
isage_edge-0.2.4.0.dist-info/LICENSE
isage_edge-0.2.4.0.dist-info/METADATA
isage_edge-0.2.4.0.dist-info/WHEEL
isage_edge-0.2.4.0.dist-info/entry_points.txt
isage_edge-0.2.4.0.dist-info/top_level.txt
isage_edge-0.2.4.0.dist-info/RECORD
