Metadata-Version: 2.1
Name: isage-edge
Version: 0.2.4.0
Summary: SAGE Edge aggregator shell - mounts LLM gateway under an optional prefix
Author-email: IntelliStream Team <intellistream@github.com>
License: MIT
Project-URL: Homepage, https://github.com/intellistream/sage-edge
Project-URL: Documentation, https://intellistream.github.io/SAGE-Pub/
Project-URL: Repository, https://github.com/intellistream/sage-edge
Project-URL: Issues, https://github.com/intellistream/sage-edge/issues
Project-URL: Changelog, https://github.com/intellistream/sage-edge/blob/main/CHANGELOG.md
Keywords: sage,edge,gateway,llm,openai
Classifier: Development Status :: 3 - Alpha
Classifier: Intended Audience :: Developers
Classifier: License :: OSI Approved :: MIT License
Classifier: Programming Language :: Python :: 3
Classifier: Programming Language :: Python :: 3.10
Classifier: Programming Language :: Python :: 3.11
Classifier: Programming Language :: Python :: 3.12
Classifier: Topic :: Scientific/Engineering :: Artificial Intelligence
Requires-Python: >=3.10
License-File: LICENSE
Requires-Dist: isage-llm-core>=0.2.0
Requires-Dist: isage-llm-gateway>=0.1.0
Requires-Dist: isage-common>=0.2.0
Requires-Dist: fastapi<1.0.0,>=0.115.0
Requires-Dist: uvicorn[standard]<1.0.0,>=0.34.0
Provides-Extra: all
Requires-Dist: isage-edge[dev,publish]; extra == "all"
Provides-Extra: dev
Requires-Dist: pytest>=7.4.0; extra == "dev"
Requires-Dist: pytest-asyncio>=0.21.0; extra == "dev"
Requires-Dist: pytest-cov>=4.0.0; extra == "dev"
Requires-Dist: ruff==0.14.6; extra == "dev"
Requires-Dist: mypy>=1.7.0; extra == "dev"
Provides-Extra: publish
Requires-Dist: isage-pypi-publisher>=0.1.0; extra == "publish"
Requires-Dist: build>=1.0.0; extra == "publish"
Requires-Dist: twine>=4.0.0; extra == "publish"
